{
  "word_count": 1797,
  "processed_language": "en",
  "personality": [
    {
      "trait_id": "big5_openness",
      "name": "Openness",
      "category": "personality",
      "percentile": 0.9224197934216848,
      "raw_score": 0.7940369274796105,
      "children": [
        {
          "trait_id": "facet_adventurousness",
          "name": "Adventurousness",
          "category": "personality",
          "percentile": 0.8420736866165835,
          "raw_score": 0.5404910537062746
        },
        {
          "trait_id": "facet_artistic_interests",
          "name": "Artistic interests",
          "category": "personality",
          "percentile": 0.8568042878248365,
          "raw_score": 0.7192928693117289
        },
        {
          "trait_id": "facet_emotionality",
          "name": "Emotionality",
          "category": "personality",
          "percentile": 0.7701376211676536,
          "raw_score": 0.6783354413721573
        },
        {
          "trait_id": "facet_imagination",
          "name": "Imagination",
          "category": "personality",
          "percentile": 0.9671210130127289,
          "raw_score": 0.8262556959073923
        },
        {
          "trait_id": "facet_intellect",
          "name": "Intellect",
          "category": "personality",
          "percentile": 0.9450390926605889,
          "raw_score": 0.6812388023896158
        },
        {
          "trait_id": "facet_liberalism",
          "name": "Authority-challenging",
          "category": "personality",
          "percentile": 0.9462210093747557,
          "raw_score": 0.597282467241611
        }
      ]
    },
    {
      "trait_id": "big5_conscientiousness",
      "name": "Conscientiousness",
      "category": "personality",
      "percentile": 0.02467975423926988,
      "raw_score": 0.5363796659272309,
      "children": [
        {
          "trait_id": "facet_achievement_striving",
          "name": "Achievement striving",
          "category": "personality",
          "percentile": 0.18651173721931202,
          "raw_score": 0.6412342445827603
        },
        {
          "trait_id": "facet_cautiousness",
          "name": "Cautiousness",
          "category": "personality",
          "percentile": 0.05413252227833737,
          "raw_score": 0.3910916426665163
        },
        {
          "trait_id": "facet_dutifulness",
          "name": "Dutifulness",
          "category": "personality",
          "percentile": 0.061192595656548776,
          "raw_score": 0.6210678668269501
        },
        {
          "trait_id": "facet_orderliness",
          "name": "Orderliness",
          "category": "personality",
          "percentile": 0.11731011043449663,
          "raw_score": 0.4552243022965883
        },
        {
          "trait_id": "facet_self_discipline",
          "name": "Self-discipline",
          "category": "personality",
          "percentile": 0.013266236510850016,
          "raw_score": 0.4649806154782293
        },
        {
          "trait_id": "facet_self_efficacy",
          "name": "Self-efficacy",
          "category": "personality",
          "percentile": 0.26654611359291647,
          "raw_score": 0.7311796315740392
        }
      ]
    },
    {
      "trait_id": "big5_extraversion",
      "name": "Extraversion",
      "category": "personality",
      "percentile": 0.26339645076147433,
      "raw_score": 0.5227634698432821,
      "children": [
        {
          "trait_id": "facet_activity_level",
          "name": "Activity level",
          "category": "personality",
          "percentile": 0.4429382334997802,
          "raw_score": 0.5330353220427023
        },
        {
          "trait_id": "facet_assertiveness",
          "name": "Assertiveness",
          "category": "personality",
          "percentile": 0.5245401633486966,
          "raw_score": 0.6471357626727461
        },
        {
          "trait_id": "facet_cheerfulness",
          "name": "Cheerfulness",
          "category": "personality",
          "percentile": 0.07514161759792293,
          "raw_score": 0.5698624372709342
        },
        {
          "trait_id": "facet_excitement_seeking",
          "name": "Excitement-seeking",
          "category": "personality",
          "percentile": 0.6152472298928181,
          "raw_score": 0.6160284750584706
        },
        {
          "trait_id": "facet_friendliness",
          "name": "Outgoing",
          "category": "personality",
          "percentile": 0.09750811986289692,
          "raw_score": 0.4954929649865014
        },
        {
          "trait_id": "facet_gregariousness",
          "name": "Gregariousness",
          "category": "personality",
          "percentile": 0.13724117378121298,
          "raw_score": 0.3971621295892575
        }
      ]
    },
    {
      "trait_id": "big5_agreeableness",
      "name": "Agreeableness",
      "category": "personality",
      "percentile": 0.22695284296262425,
      "raw_score": 0.7124254662426038,
      "children": [
        {
          "trait_id": "facet_altruism",
          "name": "Altruism",
          "category": "personality",
          "percentile": 0.7179935134823328,
          "raw_score": 0.7253272982526459
        },
        {
          "trait_id": "facet_cooperation",
          "name": "Cooperation",
          "category": "personality",
          "percentile": 0.28086168727291627,
          "raw_score": 0.5444283782932015
        },
        {
          "trait_id": "facet_modesty",
          "name": "Modesty",
          "category": "personality",
          "percentile": 0.08326381508259656,
          "raw_score": 0.3753758266409798
        },
        {
          "trait_id": "facet_morality",
          "name": "Uncompromising",
          "category": "personality",
          "percentile": 0.3925511271288635,
          "raw_score": 0.6129449404810263
        },
        {
          "trait_id": "facet_sympathy",
          "name": "Sympathy",
          "category": "personality",
          "percentile": 0.8725200370197873,
          "raw_score": 0.7069467501063665
        },
        {
          "trait_id": "facet_trust",
          "name": "Trust",
          "category": "personality",
          "percentile": 0.36164723072655236,
          "raw_score": 0.5712155427624229
        }
      ]
    },
    {
      "trait_id": "big5_neuroticism",
      "name": "Emotional range",
      "category": "personality",
      "percentile": 0.0949304950927421,
      "raw_score": 0.39346297575984285,
      "children": [
        {
          "trait_id": "facet_anger",
          "name": "Fiery",
          "category": "personality",
          "percentile": 0.886408607875566,
          "raw_score": 0.6017566117673814
        },
        {
          "trait_id": "facet_anxiety",
          "name": "Prone to worry",
          "category": "personality",
          "percentile": 0.7559504417673637,
          "raw_score": 0.6413953241037573
        },
        {
          "trait_id": "facet_depression",
          "name": "Melancholy",
          "category": "personality",
          "percentile": 0.8669919611316732,
          "raw_score": 0.5188887905965934
        },
        {
          "trait_id": "facet_immoderation",
          "name": "Immoderation",
          "category": "personality",
          "percentile": 0.6756808948024647,
          "raw_score": 0.5181050487812859
        },
        {
          "trait_id": "facet_self_consciousness",
          "name": "Self-consciousness",
          "category": "personality",
          "percentile": 0.8533897442795546,
          "raw_score": 0.6020219209117975
        },
        {
          "trait_id": "facet_vulnerability",
          "name": "Susceptible to stress",
          "category": "personality",
          "percentile": 0.8223167392004058,
          "raw_score": 0.526505685024252
        }
      ]
    }
  ],
  "needs": [
    {
      "trait_id": "need_challenge",
      "name": "Challenge",
      "category": "needs",
      "percentile": 0.6073526174674753,
      "raw_score": 0.7440022049411692
    },
    {
      "trait_id": "need_closeness",
      "name": "Closeness",
      "category": "needs",
      "percentile": 0.25111829375797307,
      "raw_score": 0.7635787601116862
    },
    {
      "trait_id": "need_curiosity",
      "name": "Curiosity",
      "category": "needs",
      "percentile": 0.9277890887702926,
      "raw_score": 0.8550633935862824
    },
    {
      "trait_id": "need_excitement",
      "name": "Excitement",
      "category": "needs",
      "percentile": 0.30136113919223484,
      "raw_score": 0.643859530559133
    },
    {
      "trait_id": "need_harmony",
      "name": "Harmony",
      "category": "needs",
      "percentile": 0.42544261708930853,
      "raw_score": 0.8027663802585403
    },
    {
      "trait_id": "need_ideal",
      "name": "Ideal",
      "category": "needs",
      "percentile": 0.6491468800025875,
      "raw_score": 0.7092563216721169
    },
    {
      "trait_id": "need_liberty",
      "name": "Liberty",
      "category": "needs",
      "percentile": 0.5030605690326115,
      "raw_score": 0.7367990329877924
    },
    {
      "trait_id": "need_love",
      "name": "Love",
      "category": "needs",
      "percentile": 0.4212597706857104,
      "raw_score": 0.7589953354036416
    },
    {
      "trait_id": "need_practicality",
      "name": "Practicality",
      "category": "needs",
      "percentile": 0.3726121547991499,
      "raw_score": 0.720752738038435
    },
    {
      "trait_id": "need_self_expression",
      "name": "Self-expression",
      "category": "needs",
      "percentile": 0.706228116188226,
      "raw_score": 0.6937501370390727
    },
    {
      "trait_id": "need_stability",
      "name": "Stability",
      "category": "needs",
      "percentile": 0.06959579318713671,
      "raw_score": 0.6873534084873936
    },
    {
      "trait_id": "need_structure",
      "name": "Structure",
      "category": "needs",
      "percentile": 0.19762935880349497,
      "raw_score": 0.6730429792654286
    }
  ],
  "values": [
    {
      "trait_id": "value_conservation",
      "name": "Conservation",
      "category": "values",
      "percentile": 0.033734013831363485,
      "raw_score": 0.5830737327113443
    },
    {
      "trait_id": "value_openness_to_change",
      "name": "Openness to change",
      "category": "values",
      "percentile": 0.8005882558786754,
      "raw_score": 0.8168032286355807
    },
    {
      "trait_id": "value_hedonism",
      "name": "Hedonism",
      "category": "values",
      "percentile": 0.46785311520654455,
      "raw_score": 0.7330391931196046
    },
    {
      "trait_id": "value_self_enhancement",
      "name": "Self-enhancement",
      "category": "values",
      "percentile": 0.5722126606363083,
      "raw_score": 0.7143160486494182
    },
    {
      "trait_id": "value_self_transcendence",
      "name": "Self-transcendence",
      "category": "values",
      "percentile": 0.4899566771886419,
      "raw_score": 0.8325486898061746
    }
  ],
  "consumption_preferences": [
    {
      "consumption_preference_category_id": "consumption_preferences_shopping",
      "name": "Purchasing Preferences",
      "consumption_preferences": [
        {
          "consumption_preference_id": "consumption_preferences_automobile_ownership_cost",
          "name": "Likely to be sensitive to ownership cost when buying automobiles",
          "score": 0.5
        },
        {
          "consumption_preference_id": "consumption_preferences_automobile_safety",
          "name": "Likely to prefer safety when buying automobiles",
          "score": 0
        },
        {
          "consumption_preference_id": "consumption_preferences_automobile_resale_value",
          "name": "Likely to prefer resale value when buying automobiles",
          "score": 0
        },
        {
          "consumption_preference_id": "consumption_preferences_clothes_quality",
          "name": "Likely to prefer quality when buying clothes",
          "score": 0
        },
        {
          "consumption_preference_id": "consumption_preferences_clothes_style",
          "name": "Likely to prefer style when buying clothes",
          "score": 1
        },
        {
          "consumption_preference_id": "consumption_preferences_clothes_comfort",
          "name": "Likely to prefer comfort when buying clothes",
          "score": 0
        },
        {
          "consumption_preference_id": "consumption_preferences_influence_brand_name",
          "name": "Likely to be influenced by brand name when making product purchases",
          "score": 0
        },
        {
          "consumption_preference_id": "consumption_preferences_influence_utility",
          "name": "Likely to be influenced by product utility when making product purchases",
          "score": 1
        },
        {
          "consumption_preference_id": "consumption_preferences_influence_online_ads",
          "name": "Likely to be influenced by online ads when making product purchases",
          "score": 1
        },
        {
          "consumption_preference_id": "consumption_preferences_influence_social_media",
          "name": "Likely to be influenced by social media when making product purchases",
          "score": 1
        },
        {
          "consumption_preference_id": "consumption_preferences_influence_family_members",
          "name": "Likely to be influenced by family when making product purchases",
          "score": 0
        },
        {
          "consumption_preference_id": "consumption_preferences_spur_of_moment",
          "name": "Likely to indulge in spur of the moment purchases",
          "score": 1
        },
        {
          "consumption_preference_id": "consumption_preferences_credit_card_payment",
          "name": "Likely to prefer using credit cards for shopping",
          "score": 0
        }
      ]
    },
    {
      "consumption_preference_category_id": "consumption_preferences_health_and_activity",
      "name": "Health & Activity Preferences",
      "consumption_preferences": [
        {
          "consumption_preference_id": "consumption_preferences_eat_out",
          "name": "Likely to eat out frequently",
          "score": 1
        },
        {
          "consumption_preference_id": "consumption_preferences_fast_food_frequency",
          "name": "Likely to eat fast food frequently",
          "score": 1
        },
        {
          "consumption_preference_id": "consumption_preferences_gym_membership",
          "name": "Likely to have a gym membership",
          "score": 0
        },
        {
          "consumption_preference_id": "consumption_preferences_adventurous_sports",
          "name": "Likely to like adventurous sports",
          "score": 0
        },
        {
          "consumption_preference_id": "consumption_preferences_outdoor",
          "name": "Likely to like outdoor activities",
          "score": 0.5
        }
      ]
    },
    {
      "consumption_preference_category_id": "consumption_preferences_environmental_concern",
      "name": "Environmental Concern Preferences",
      "consumption_preferences": [
        {
          "consumption_preference_id": "consumption_preferences_concerned_environment",
          "name": "Likely to be concerned about the environment",
          "score": 1
        }
      ]
    },
    {
      "consumption_preference_category_id": "consumption_preferences_entrepreneurship",
      "name": "Entrepreneurship Preferences",
      "consumption_preferences": [
        {
          "consumption_preference_id": "consumption_preferences_start_business",
          "name": "Likely to consider starting a business in next few years",
          "score": 0
        }
      ]
    },
    {
      "consumption_preference_category_id": "consumption_preferences_movie",
      "name": "Movie Preferences",
      "consumption_preferences": [
        {
          "consumption_preference_id": "consumption_preferences_movie_romance",
          "name": "Likely to like romance movies",
          "score": 0
        },
        {
          "consumption_preference_id": "consumption_preferences_movie_adventure",
          "name": "Likely to like adventure movies",
          "score": 0
        },
        {
          "consumption_preference_id": "consumption_preferences_movie_horror",
          "name": "Likely to like horror movies",
          "score": 0
        },
        {
          "consumption_preference_id": "consumption_preferences_movie_musical",
          "name": "Likely to like musical movies",
          "score": 1
        },
        {
          "consumption_preference_id": "consumption_preferences_movie_historical",
          "name": "Likely to like historical movies",
          "score": 1
        },
        {
          "consumption_preference_id": "consumption_preferences_movie_science_fiction",
          "name": "Likely to like science-fiction movies",
          "score": 0
        },
        {
          "consumption_preference_id": "consumption_preferences_movie_war",
          "name": "Likely to like war movies",
          "score": 0
        },
        {
          "consumption_preference_id": "consumption_preferences_movie_drama",
          "name": "Likely to like drama movies",
          "score": 0
        },
        {
          "consumption_preference_id": "consumption_preferences_movie_action",
          "name": "Likely to like action movies",
          "score": 0
        },
        {
          "consumption_preference_id": "consumption_preferences_movie_documentary",
          "name": "Likely to like documentary movies",
          "score": 1
        }
      ]
    },
    {
      "consumption_preference_category_id": "consumption_preferences_music",
      "name": "Music Preferences",
      "consumption_preferences": [
        {
          "consumption_preference_id": "consumption_preferences_music_rap",
          "name": "Likely to like rap music",
          "score": 0.5
        },
        {
          "consumption_preference_id": "consumption_preferences_music_country",
          "name": "Likely to like country music",
          "score": 0
        },
        {
          "consumption_preference_id": "consumption_preferences_music_r_b",
          "name": "Likely to like R&B music",
          "score": 0.5
        },
        {
          "consumption_preference_id": "consumption_preferences_music_hip_hop",
          "name": "Likely to like hip hop music",
          "score": 1
        },
        {
          "consumption_preference_id": "consumption_preferences_music_live_event",
          "name": "Likely to attend live musical events",
          "score": 1
        },
        {
          "consumption_preference_id": "consumption_preferences_music_playing",
          "name": "Likely to have experience playing music",
          "score": 1
        },
        {
          "consumption_preference_id": "consumption_preferences_music_latin",
          "name": "Likely to like Latin music",
          "score": 1
        },
        {
          "consumption_preference_id": "consumption_preferences_music_rock",
          "name": "Likely to like rock music",
          "score": 0
        },
        {
          "consumption_preference_id": "consumption_preferences_music_classical",
          "name": "Likely to like classical music",
          "score": 0.5
        }
      ]
    },
    {
      "consumption_preference_category_id": "consumption_preferences_reading",
      "name": "Reading Preferences",
      "consumption_preferences": [
        {
          "consumption_preference_id": "consumption_preferences_read_frequency",
          "name": "Likely to read often",
          "score": 0
        },
        {
          "consumption_preference_id": "consumption_preferences_read_motive_enjoyment",
          "name": "Likely to read for enjoyment",
          "score": 1
        },
        {
          "consumption_preference_id": "consumption_preferences_read_motive_information",
          "name": "Likely to read for information",
          "score": 1
        },
        {
          "consumption_preference_id": "consumption_preferences_books_entertainment_magazines",
          "name": "Likely to read entertainment magazines",
          "score": 1
        },
        {
          "consumption_preference_id": "consumption_preferences_books_non_fiction",
          "name": "Likely to read non-fiction books",
          "score": 1
        },
        {
          "consumption_preference_id": "consumption_preferences_read_motive_mandatory",
          "name": "Likely to do mandatory reading only",
          "score": 1
        },
        {
          "consumption_preference_id": "consumption_preferences_read_motive_relaxation",
          "name": "Likely to read for relaxation",
          "score": 0
        },
        {
          "consumption_preference_id": "consumption_preferences_books_financial_investing",
          "name": "Likely to read financial investment books",
          "score": 0
        },
        {
          "consumption_preference_id": "consumption_preferences_books_autobiographies",
          "name": "Likely to read autobiographical books",
          "score": 0
        }
      ]
    },
    {
      "consumption_preference_category_id": "consumption_preferences_volunteering",
      "name": "Volunteering Preferences",
      "consumption_preferences": [
        {
          "consumption_preference_id": "consumption_preferences_volunteer",
          "name": "Likely to volunteer for social causes",
          "score": 0
        },
        {
          "consumption_preference_id": "consumption_preferences_volunteering_time",
          "name": "Likely to have spent time volunteering",
          "score": 0
        },
        {
          "consumption_preference_id": "consumption_preferences_volunteer_learning",
          "name": "Likely to volunteer to learn about social causes",
          "score": 1
        }
      ]
    }
  ],
  "warnings": []
}
