{
  "word_count": 1323,
  "processed_language": "en",
  "personality": [
    {
      "trait_id": "big5_openness",
      "name": "Openness",
      "category": "personality",
      "percentile": 0.11507474509550902,
      "raw_score": 0.7103404376037211,
      "children": [
        {
          "trait_id": "facet_adventurousness",
          "name": "Adventurousness",
          "category": "personality",
          "percentile": 0.32114669238110427,
          "raw_score": 0.4882973390830717
        },
        {
          "trait_id": "facet_artistic_interests",
          "name": "Artistic interests",
          "category": "personality",
          "percentile": 0.3582638131006788,
          "raw_score": 0.6469432245221021
        },
        {
          "trait_id": "facet_emotionality",
          "name": "Emotionality",
          "category": "personality",
          "percentile": 0.5497012165848266,
          "raw_score": 0.6532873550441707
        },
        {
          "trait_id": "facet_imagination",
          "name": "Imagination",
          "category": "personality",
          "percentile": 0.8092462212694962,
          "raw_score": 0.7783263605716267
        },
        {
          "trait_id": "facet_intellect",
          "name": "Intellect",
          "category": "personality",
          "percentile": 0.01229344835256957,
          "raw_score": 0.5032020560462032
        },
        {
          "trait_id": "facet_liberalism",
          "name": "Authority-challenging",
          "category": "personality",
          "percentile": 0.230052298810561,
          "raw_score": 0.4790247165049835
        }
      ]
    },
    {
      "trait_id": "big5_conscientiousness",
      "name": "Conscientiousness",
      "category": "personality",
      "percentile": 0.43161354234451516,
      "raw_score": 0.6200162927630332,
      "children": [
        {
          "trait_id": "facet_achievement_striving",
          "name": "Achievement striving",
          "category": "personality",
          "percentile": 0.6323475044067615,
          "raw_score": 0.7062977705860056
        },
        {
          "trait_id": "facet_cautiousness",
          "name": "Cautiousness",
          "category": "personality",
          "percentile": 0.13944073584846473,
          "raw_score": 0.4241191818216235
        },
        {
          "trait_id": "facet_dutifulness",
          "name": "Dutifulness",
          "category": "personality",
          "percentile": 0.16682357368584844,
          "raw_score": 0.6352239787146218
        },
        {
          "trait_id": "facet_orderliness",
          "name": "Orderliness",
          "category": "personality",
          "percentile": 0.633392151898759,
          "raw_score": 0.5053208514667034
        },
        {
          "trait_id": "facet_self_discipline",
          "name": "Self-discipline",
          "category": "personality",
          "percentile": 0.42467762470633497,
          "raw_score": 0.5616053876696399
        },
        {
          "trait_id": "facet_self_efficacy",
          "name": "Self-efficacy",
          "category": "personality",
          "percentile": 0.8948174156600901,
          "raw_score": 0.7971500793068519
        }
      ]
    },
    {
      "trait_id": "big5_extraversion",
      "name": "Extraversion",
      "category": "personality",
      "percentile": 0.9290744529859518,
      "raw_score": 0.616555165928626,
      "children": [
        {
          "trait_id": "facet_activity_level",
          "name": "Activity level",
          "category": "personality",
          "percentile": 0.8187898893183303,
          "raw_score": 0.5869819919377185
        },
        {
          "trait_id": "facet_assertiveness",
          "name": "Assertiveness",
          "category": "personality",
          "percentile": 0.8389943504976597,
          "raw_score": 0.693565779718863
        },
        {
          "trait_id": "facet_cheerfulness",
          "name": "Cheerfulness",
          "category": "personality",
          "percentile": 0.9175755179345568,
          "raw_score": 0.6647501847839394
        },
        {
          "trait_id": "facet_excitement_seeking",
          "name": "Excitement-seeking",
          "category": "personality",
          "percentile": 0.9063123514445064,
          "raw_score": 0.6595039173837388
        },
        {
          "trait_id": "facet_friendliness",
          "name": "Outgoing",
          "category": "personality",
          "percentile": 0.8105314442764766,
          "raw_score": 0.6046183333912615
        },
        {
          "trait_id": "facet_gregariousness",
          "name": "Gregariousness",
          "category": "personality",
          "percentile": 0.8854543036425984,
          "raw_score": 0.5151750664329244
        }
      ]
    },
    {
      "trait_id": "big5_agreeableness",
      "name": "Agreeableness",
      "category": "personality",
      "percentile": 0.8027172588568594,
      "raw_score": 0.7760441561655164,
      "children": [
        {
          "trait_id": "facet_altruism",
          "name": "Altruism",
          "category": "personality",
          "percentile": 0.5772000214232804,
          "raw_score": 0.711920990454949
        },
        {
          "trait_id": "facet_cooperation",
          "name": "Cooperation",
          "category": "personality",
          "percentile": 0.0937721043787737,
          "raw_score": 0.4999900042593165
        },
        {
          "trait_id": "facet_modesty",
          "name": "Modesty",
          "category": "personality",
          "percentile": 0.09878757433279756,
          "raw_score": 0.38038638053982976
        },
        {
          "trait_id": "facet_morality",
          "name": "Uncompromising",
          "category": "personality",
          "percentile": 0.13904295333493683,
          "raw_score": 0.5746336745070384
        },
        {
          "trait_id": "facet_sympathy",
          "name": "Sympathy",
          "category": "personality",
          "percentile": 0.28902419776253524,
          "raw_score": 0.6422385827054798
        },
        {
          "trait_id": "facet_trust",
          "name": "Trust",
          "category": "personality",
          "percentile": 0.7867306862296557,
          "raw_score": 0.6185588811679888
        }
      ]
    },
    {
      "trait_id": "big5_neuroticism",
      "name": "Emotional range",
      "category": "personality",
      "percentile": 0.23739825834232892,
      "raw_score": 0.427077097064404,
      "children": [
        {
          "trait_id": "facet_anger",
          "name": "Fiery",
          "category": "personality",
          "percentile": 0.873283108927595,
          "raw_score": 0.5981692805299487
        },
        {
          "trait_id": "facet_anxiety",
          "name": "Prone to worry",
          "category": "personality",
          "percentile": 0.751596500605928,
          "raw_score": 0.6404533120353362
        },
        {
          "trait_id": "facet_depression",
          "name": "Melancholy",
          "category": "personality",
          "percentile": 0.28436842766912657,
          "raw_score": 0.4123416969803314
        },
        {
          "trait_id": "facet_immoderation",
          "name": "Immoderation",
          "category": "personality",
          "percentile": 0.3612784846081658,
          "raw_score": 0.48694629640720954
        },
        {
          "trait_id": "facet_self_consciousness",
          "name": "Self-consciousness",
          "category": "personality",
          "percentile": 0.4566732895761069,
          "raw_score": 0.540988594868432
        },
        {
          "trait_id": "facet_vulnerability",
          "name": "Susceptible to stress",
          "category": "personality",
          "percentile": 0.5420907359541127,
          "raw_score": 0.4743562513684453
        }
      ]
    }
  ],
  "needs": [
    {
      "trait_id": "need_challenge",
      "name": "Challenge",
      "category": "needs",
      "percentile": 0.995933840942068,
      "raw_score": 0.8504770705081565
    },
    {
      "trait_id": "need_closeness",
      "name": "Closeness",
      "category": "needs",
      "percentile": 0.857126200054696,
      "raw_score": 0.8407434578067086
    },
    {
      "trait_id": "need_curiosity",
      "name": "Curiosity",
      "category": "needs",
      "percentile": 0.7090367623915559,
      "raw_score": 0.8311407763025885
    },
    {
      "trait_id": "need_excitement",
      "name": "Excitement",
      "category": "needs",
      "percentile": 0.9022585458711048,
      "raw_score": 0.7880361769066411
    },
    {
      "trait_id": "need_harmony",
      "name": "Harmony",
      "category": "needs",
      "percentile": 0.8886202156364281,
      "raw_score": 0.8513575977598082
    },
    {
      "trait_id": "need_ideal",
      "name": "Ideal",
      "category": "needs",
      "percentile": 0.9785720738038555,
      "raw_score": 0.7872919320160139
    },
    {
      "trait_id": "need_liberty",
      "name": "Liberty",
      "category": "needs",
      "percentile": 0.819484667770398,
      "raw_score": 0.7707294832037138
    },
    {
      "trait_id": "need_love",
      "name": "Love",
      "category": "needs",
      "percentile": 0.8971553240919472,
      "raw_score": 0.830221405241872
    },
    {
      "trait_id": "need_practicality",
      "name": "Practicality",
      "category": "needs",
      "percentile": 0.8704004973153158,
      "raw_score": 0.7521505774641147
    },
    {
      "trait_id": "need_self_expression",
      "name": "Self-expression",
      "category": "needs",
      "percentile": 0.9407207895614138,
      "raw_score": 0.7288829777161141
    },
    {
      "trait_id": "need_stability",
      "name": "Stability",
      "category": "needs",
      "percentile": 0.830979492287887,
      "raw_score": 0.7649598427795758
    },
    {
      "trait_id": "need_structure",
      "name": "Structure",
      "category": "needs",
      "percentile": 0.8082941146631037,
      "raw_score": 0.7196969284473326
    }
  ],
  "values": [
    {
      "trait_id": "value_conservation",
      "name": "Conservation",
      "category": "values",
      "percentile": 0.9630921567874944,
      "raw_score": 0.7459879967421416
    },
    {
      "trait_id": "value_openness_to_change",
      "name": "Openness to change",
      "category": "values",
      "percentile": 0.8378290590539791,
      "raw_score": 0.822273156421304
    },
    {
      "trait_id": "value_hedonism",
      "name": "Hedonism",
      "category": "values",
      "percentile": 0.9646593286596912,
      "raw_score": 0.8536961324847306
    },
    {
      "trait_id": "value_self_enhancement",
      "name": "Self-enhancement",
      "category": "values",
      "percentile": 0.994290022594081,
      "raw_score": 0.8173093700589511
    },
    {
      "trait_id": "value_self_transcendence",
      "name": "Self-transcendence",
      "category": "values",
      "percentile": 0.59769244640013,
      "raw_score": 0.8369880136341175
    }
  ],
  "consumption_preferences": [
    {
      "consumption_preference_category_id": "consumption_preferences_shopping",
      "name": "Purchasing Preferences",
      "consumption_preferences": [
        {
          "consumption_preference_id": "consumption_preferences_automobile_ownership_cost",
          "name": "Likely to be sensitive to ownership cost when buying automobiles",
          "score": 0
        },
        {
          "consumption_preference_id": "consumption_preferences_automobile_safety",
          "name": "Likely to prefer safety when buying automobiles",
          "score": 0.5
        },
        {
          "consumption_preference_id": "consumption_preferences_automobile_resale_value",
          "name": "Likely to prefer resale value when buying automobiles",
          "score": 0.5
        },
        {
          "consumption_preference_id": "consumption_preferences_clothes_quality",
          "name": "Likely to prefer quality when buying clothes",
          "score": 0
        },
        {
          "consumption_preference_id": "consumption_preferences_clothes_style",
          "name": "Likely to prefer style when buying clothes",
          "score": 1
        },
        {
          "consumption_preference_id": "consumption_preferences_clothes_comfort",
          "name": "Likely to prefer comfort when buying clothes",
          "score": 0
        },
        {
          "consumption_preference_id": "consumption_preferences_influence_brand_name",
          "name": "Likely to be influenced by brand name when making product purchases",
          "score": 1
        },
        {
          "consumption_preference_id": "consumption_preferences_influence_utility",
          "name": "Likely to be influenced by product utility when making product purchases",
          "score": 0.5
        },
        {
          "consumption_preference_id": "consumption_preferences_influence_online_ads",
          "name": "Likely to be influenced by online ads when making product purchases",
          "score": 1
        },
        {
          "consumption_preference_id": "consumption_preferences_influence_social_media",
          "name": "Likely to be influenced by social media when making product purchases",
          "score": 1
        },
        {
          "consumption_preference_id": "consumption_preferences_influence_family_members",
          "name": "Likely to be influenced by family when making product purchases",
          "score": 0
        },
        {
          "consumption_preference_id": "consumption_preferences_spur_of_moment",
          "name": "Likely to indulge in spur of the moment purchases",
          "score": 1
        },
        {
          "consumption_preference_id": "consumption_preferences_credit_card_payment",
          "name": "Likely to prefer using credit cards for shopping",
          "score": 0
        }
      ]
    },
    {
      "consumption_preference_category_id": "consumption_preferences_health_and_activity",
      "name": "Health & Activity Preferences",
      "consumption_preferences": [
        {
          "consumption_preference_id": "consumption_preferences_eat_out",
          "name": "Likely to eat out frequently",
          "score": 1
        },
        {
          "consumption_preference_id": "consumption_preferences_fast_food_frequency",
          "name": "Likely to eat fast food frequently",
          "score": 1
        },
        {
          "consumption_preference_id": "consumption_preferences_gym_membership",
          "name": "Likely to have a gym membership",
          "score": 1
        },
        {
          "consumption_preference_id": "consumption_preferences_adventurous_sports",
          "name": "Likely to like adventurous sports",
          "score": 1
        },
        {
          "consumption_preference_id": "consumption_preferences_outdoor",
          "name": "Likely to like outdoor activities",
          "score": 1
        }
      ]
    },
    {
      "consumption_preference_category_id": "consumption_preferences_environmental_concern",
      "name": "Environmental Concern Preferences",
      "consumption_preferences": [
        {
          "consumption_preference_id": "consumption_preferences_concerned_environment",
          "name": "Likely to be concerned about the environment",
          "score": 0
        }
      ]
    },
    {
      "consumption_preference_category_id": "consumption_preferences_entrepreneurship",
      "name": "Entrepreneurship Preferences",
      "consumption_preferences": [
        {
          "consumption_preference_id": "consumption_preferences_start_business",
          "name": "Likely to consider starting a business in next few years",
          "score": 1
        }
      ]
    },
    {
      "consumption_preference_category_id": "consumption_preferences_movie",
      "name": "Movie Preferences",
      "consumption_preferences": [
        {
          "consumption_preference_id": "consumption_preferences_movie_romance",
          "name": "Likely to like romance movies",
          "score": 1
        },
        {
          "consumption_preference_id": "consumption_preferences_movie_adventure",
          "name": "Likely to like adventure movies",
          "score": 0
        },
        {
          "consumption_preference_id": "consumption_preferences_movie_horror",
          "name": "Likely to like horror movies",
          "score": 1
        },
        {
          "consumption_preference_id": "consumption_preferences_movie_musical",
          "name": "Likely to like musical movies",
          "score": 0
        },
        {
          "consumption_preference_id": "consumption_preferences_movie_historical",
          "name": "Likely to like historical movies",
          "score": 0
        },
        {
          "consumption_preference_id": "consumption_preferences_movie_science_fiction",
          "name": "Likely to like science-fiction movies",
          "score": 0
        },
        {
          "consumption_preference_id": "consumption_preferences_movie_war",
          "name": "Likely to like war movies",
          "score": 0
        },
        {
          "consumption_preference_id": "consumption_preferences_movie_drama",
          "name": "Likely to like drama movies",
          "score": 1
        },
        {
          "consumption_preference_id": "consumption_preferences_movie_action",
          "name": "Likely to like action movies",
          "score": 0
        },
        {
          "consumption_preference_id": "consumption_preferences_movie_documentary",
          "name": "Likely to like documentary movies",
          "score": 0
        }
      ]
    },
    {
      "consumption_preference_category_id": "consumption_preferences_music",
      "name": "Music Preferences",
      "consumption_preferences": [
        {
          "consumption_preference_id": "consumption_preferences_music_rap",
          "name": "Likely to like rap music",
          "score": 1
        },
        {
          "consumption_preference_id": "consumption_preferences_music_country",
          "name": "Likely to like country music",
          "score": 1
        },
        {
          "consumption_preference_id": "consumption_preferences_music_r_b",
          "name": "Likely to like R&B music",
          "score": 1
        },
        {
          "consumption_preference_id": "consumption_preferences_music_hip_hop",
          "name": "Likely to like hip hop music",
          "score": 1
        },
        {
          "consumption_preference_id": "consumption_preferences_music_live_event",
          "name": "Likely to attend live musical events",
          "score": 0
        },
        {
          "consumption_preference_id": "consumption_preferences_music_playing",
          "name": "Likely to have experience playing music",
          "score": 0
        },
        {
          "consumption_preference_id": "consumption_preferences_music_latin",
          "name": "Likely to like Latin music",
          "score": 0.5
        },
        {
          "consumption_preference_id": "consumption_preferences_music_rock",
          "name": "Likely to like rock music",
          "score": 0
        },
        {
          "consumption_preference_id": "consumption_preferences_music_classical",
          "name": "Likely to like classical music",
          "score": 0
        }
      ]
    },
    {
      "consumption_preference_category_id": "consumption_preferences_reading",
      "name": "Reading Preferences",
      "consumption_preferences": [
        {
          "consumption_preference_id": "consumption_preferences_read_frequency",
          "name": "Likely to read often",
          "score": 0
        },
        {
          "consumption_preference_id": "consumption_preferences_read_motive_enjoyment",
          "name": "Likely to read for enjoyment",
          "score": 0
        },
        {
          "consumption_preference_id": "consumption_preferences_read_motive_information",
          "name": "Likely to read for information",
          "score": 0
        },
        {
          "consumption_preference_id": "consumption_preferences_books_entertainment_magazines",
          "name": "Likely to read entertainment magazines",
          "score": 1
        },
        {
          "consumption_preference_id": "consumption_preferences_books_non_fiction",
          "name": "Likely to read non-fiction books",
          "score": 0
        },
        {
          "consumption_preference_id": "consumption_preferences_read_motive_mandatory",
          "name": "Likely to do mandatory reading only",
          "score": 1
        },
        {
          "consumption_preference_id": "consumption_preferences_read_motive_relaxation",
          "name": "Likely to read for relaxation",
          "score": 0
        },
        {
          "consumption_preference_id": "consumption_preferences_books_financial_investing",
          "name": "Likely to read financial investment books",
          "score": 1
        },
        {
          "consumption_preference_id": "consumption_preferences_books_autobiographies",
          "name": "Likely to read autobiographical books",
          "score": 0
        }
      ]
    },
    {
      "consumption_preference_category_id": "consumption_preferences_volunteering",
      "name": "Volunteering Preferences",
      "consumption_preferences": [
        {
          "consumption_preference_id": "consumption_preferences_volunteer",
          "name": "Likely to volunteer for social causes",
          "score": 0
        },
        {
          "consumption_preference_id": "consumption_preferences_volunteering_time",
          "name": "Likely to have spent time volunteering",
          "score": 0
        },
        {
          "consumption_preference_id": "consumption_preferences_volunteer_learning",
          "name": "Likely to volunteer to learn about social causes",
          "score": 0
        }
      ]
    }
  ],
  "warnings": []
}
